cgiserver/__init__.py
cgiserver/__version__.py
cgiserver/http_parser.py
cgiserver/http_server.py
cgiserver/http_session.py
cgiserver/logging/__init__.py
cgiserver/logging/logger.py
cgiserver/router/__init__.py
cgiserver/router/router.py
cgiserver/setting/__init__.py
cgiserver/setting/setting.py
cgiserver/utils/__init__.py
cgiserver/utils/attrdict.py
cgiserver/utils/exceptions.py
cgiserver/utils/loader.py
cgiserver/utils/queue.py
cgiserver/utils/status.py
tests/__init__.py
tests/test_functionality.py
tests/test_parser.py
tests/test_router.py
cgi_server-1.2.5.dist-info/LICENSE
cgi_server-1.2.5.dist-info/METADATA
cgi_server-1.2.5.dist-info/WHEEL
cgi_server-1.2.5.dist-info/top_level.txt
cgi_server-1.2.5.dist-info/RECORD
