Metadata-Version: 2.1
Name: cgi-server
Version: 1.2.5
Summary: multi thread cgi server using python3
Home-page: https://github.com/0x404/cgi-server
Author: zengqunhong; xuzheyuan; luxinbo;
Author-email: zengqunhong@gmail.com
License: UNKNOWN
Platform: UNKNOWN
Requires-Python: >=3.9
License-File: LICENSE
Requires-Dist: pylint (==2.14.4)
Requires-Dist: black (==22.6.0)
Requires-Dist: pytest (==7.1.3)
Requires-Dist: coloredlogs (==15.0.1)
